LICENSE.txt
MANIFEST.in
README.md
setup.cfg
setup.py
aiospotify/__init__.py
aiospotify/aiospotify.py
aiospotify/connectors.py
aiospotify/endpoints.py
aiospotify.egg-info/PKG-INFO
aiospotify.egg-info/SOURCES.txt
aiospotify.egg-info/dependency_links.txt
aiospotify.egg-info/requires.txt
aiospotify.egg-info/top_level.txt