Metadata-Version: 1.1
Name: aiospotify
Version: 0.1.0
Summary: Aiospotify is a request-agnostic wrapper for Spotify's Web API.
Home-page: https://github.com/jdr023/aiospotify
Author: whitespace
Author-email: UNKNOWN
License: MIT
Download-URL: https://github.com/jdr023/aiospotify/archive/v0.1.0.tar.gz
Keywords: aiospotify,spotify,asyncio,aiohttp,api,library
Platform: UNKNOWN
Classifier: Development Status :: 3 - Alpha
Classifier: Intended Audience :: Developers
Classifier: Topic :: Software Development :: Libraries :: Python Modules
Classifier: License :: OSI Approved :: MIT License
Classifier: Programming Language :: Python :: 3.6
